spec/plugin_metadata.schema.json
spec/schemas/card_anchor_v1.schema.json
spec/schemas/dr_provider_v1.schema.json
spec/schemas/ghidra_analysis_v1.schema.json
spec/schemas/graph_delta_v1.schema.json
spec/schemas/graphjson_v1.schema.json
spec/schemas/manifest.schema.json
spec/schemas/model_provider_v1.schema.json
spec/schemas/object_storage_v1.schema.json
spec/schemas/provenance_v1.schema.json
spec/wit/dr_provider_v1.wit
spec/wit/graph_adapter_v1.wit
spec/wit/object_storage_v1.wit
yams_sdk/__init__.py
yams_sdk/abi.py
yams_sdk/base.py
yams_sdk/decorators.py
yams_sdk/graph_client.py
yams_sdk/graph_store.py
yams_sdk/hound.py
yams_sdk/interfaces.py
yams_sdk/ipc.py
yams_sdk/models.py
yams_sdk/schemas.py
yams_sdk/testing.py
yams_sdk/transports.py
yams_sdk-0.0.1.dist-info/METADATA
yams_sdk-0.0.1.dist-info/WHEEL
yams_sdk-0.0.1.dist-info/licenses/LICENSE
yams_sdk-0.0.1.dist-info/RECORD
