Metadata-Version: 2.4
Name: yams-sdk
Version: 0.0.1
Summary: Python SDK for YAMS (Yet Another Memory System) - Build plugins and clients
Project-URL: Homepage, https://sr.ht/~trvon/yams/
Project-URL: Repository, https://git.sr.ht/~trvon/yams-sdk
Project-URL: Documentation, https://git.sr.ht/~trvon/yams-sdk/tree/main/item/README.md
Project-URL: Issues, https://todo.sr.ht/~trvon/yams
Author: YAMS Project
License: GPL-3.0-only
License-File: LICENSE
Keywords: embeddings,indexing,json-rpc,memory,plugin,sdk,search,yams
Classifier: Development Status :: 3 - Alpha
Classifier: Intended Audience :: Developers
Classifier: License :: OSI Approved :: GNU General Public License v3 (GPLv3)
Classifier: Operating System :: OS Independent
Classifier: Programming Language :: Python :: 3
Classifier: Programming Language :: Python :: 3.9
Classifier: Programming Language :: Python :: 3.10
Classifier: Programming Language :: Python :: 3.11
Classifier: Programming Language :: Python :: 3.12
Classifier: Topic :: Database :: Database Engines/Servers
Classifier: Topic :: Software Development :: Libraries :: Python Modules
Classifier: Topic :: Text Processing :: Indexing
Requires-Python: >=3.9
Requires-Dist: jsonschema>=4.0.0
